odoo8_addon_l10n_it_regions-8.0.1.0.2-nspkg.pth
odoo_addons/l10n_it_regions/README.rst
odoo_addons/l10n_it_regions/__init__.py
odoo_addons/l10n_it_regions/__openerp__.py
odoo_addons/l10n_it_regions/i18n/it.po
odoo_addons/l10n_it_regions/i18n/l10n_it_regions.pot
odoo_addons/l10n_it_regions/i18n/sl.po
odoo_addons/l10n_it_regions/models/__init__.py
odoo_addons/l10n_it_regions/models/partner.py
odoo_addons/l10n_it_regions/models/region.py
odoo_addons/l10n_it_regions/security/ir.model.access.csv
odoo_addons/l10n_it_regions/static/description/icon.png
odoo_addons/l10n_it_regions/views/partner_view.xml
odoo_addons/l10n_it_regions/views/region_view.xml
odoo_addons/l10n_it_regions/wizards/__init__.py
odoo_addons/l10n_it_regions/wizards/geonames_import.py
odoo8_addon_l10n_it_regions-8.0.1.0.2.dist-info/METADATA
odoo8_addon_l10n_it_regions-8.0.1.0.2.dist-info/WHEEL
odoo8_addon_l10n_it_regions-8.0.1.0.2.dist-info/namespace_packages.txt
odoo8_addon_l10n_it_regions-8.0.1.0.2.dist-info/top_level.txt
odoo8_addon_l10n_it_regions-8.0.1.0.2.dist-info/RECORD
