Metadata-Version: 2.1
Name: odoo8-addon-l10n-it-regions
Version: 8.0.1.0.2
Summary: Import Italian regions from Geonames
Home-page: http://odoo-community.org
Author: Odoo Community Association (OCA)
Author-email: support@odoo-community.org
License: AGPL-3
Platform: UNKNOWN
Classifier: Programming Language :: Python
Classifier: Framework :: Odoo
Classifier: License :: OSI Approved :: GNU Affero General Public License v3
Requires-Python: ~=2.7
Requires-Dist: odoo8-addon-base-location-geonames-import
Requires-Dist: odoo8-addon-l10n-it-base-location-geonames-import
Requires-Dist: odoo (<9.0a,>=8.0a)
